corpus_builder/__init__.py
corpus_builder/__main__.py
corpus_builder/builder.py
corpus_builder/builder_importer.py
corpus_builder/corpus_exporter.py
corpus_builder/exceptions.py
corpus_builder/grammar.py
corpus_builder/rule.py
corpus_builder/text_augmentation.py
corpus_builder/visualize.py
corpus_builder-0.2.0.dist-info/LICENCE
corpus_builder-0.2.0.dist-info/METADATA
corpus_builder-0.2.0.dist-info/WHEEL
corpus_builder-0.2.0.dist-info/top_level.txt
corpus_builder-0.2.0.dist-info/RECORD
