Metadata-Version: 2.1
Name: corpus-builder
Version: 0.2.0
Summary: A package for semi automatic corpus building
Home-page: https://github.com/popop12342/corpus-builber
Author: Felipe Pinna
Author-email: felipepinna17@gmail.com
Classifier: Programming Language :: Python :: 3
Classifier: License :: OSI Approved :: MIT License
Classifier: Operating System :: OS Independent
Requires-Python: >=3.6
License-File: LICENCE
